color_lib/__init__.py
color_lib-0.0.3.dist-info/METADATA
color_lib-0.0.3.dist-info/WHEEL
color_lib-0.0.3.dist-info/top_level.txt
color_lib-0.0.3.dist-info/RECORD
