Metadata-Version: 2.1
Name: color-lib
Version: 0.0.3
Summary: Highlight your terminal output like a pro!
Home-page: https://github.com/RailRunner16/color_lib
Author: Landon Gravat
Author-email: railinator4903@gmail.com
License: UNKNOWN
Platform: UNKNOWN
Classifier: Programming Language :: Python :: 3
Classifier: License :: OSI Approved :: MIT License
Classifier: Operating System :: OS Independent
